odoo/addons/account_invoice_recompute_tax/README.rst
odoo/addons/account_invoice_recompute_tax/__init__.py
odoo/addons/account_invoice_recompute_tax/__manifest__.py
odoo/addons/account_invoice_recompute_tax/i18n/fr.po
odoo/addons/account_invoice_recompute_tax/models/__init__.py
odoo/addons/account_invoice_recompute_tax/models/account_invoice.py
odoo/addons/account_invoice_recompute_tax/readme/CONTRIBUTORS.rst
odoo/addons/account_invoice_recompute_tax/readme/DESCRIPTION.rst
odoo/addons/account_invoice_recompute_tax/readme/DEVELOP.rst
odoo/addons/account_invoice_recompute_tax/static/description/account_invoice_form.png
odoo/addons/account_invoice_recompute_tax/static/description/icon.png
odoo/addons/account_invoice_recompute_tax/static/description/index.html
odoo/addons/account_invoice_recompute_tax/views/view_account_invoice.xml
odoo12_addon_account_invoice_recompute_tax-12.0.1.0.1.dist-info/METADATA
odoo12_addon_account_invoice_recompute_tax-12.0.1.0.1.dist-info/WHEEL
odoo12_addon_account_invoice_recompute_tax-12.0.1.0.1.dist-info/top_level.txt
odoo12_addon_account_invoice_recompute_tax-12.0.1.0.1.dist-info/RECORD
